{"blog-sidebar":{"search-2":{"title":"Search here"},"categories-2":{"title":"Category","count":0,"hierarchical":0,"dropdown":0},"rr-latest-posts-2":{"title":"Recent Posts","count":"3","posts_order":"DESC"},"tag_cloud-2":{"title":"Tags","count":0,"taxonomy":"post_tag"}},"rr-service-sidebar":{"rr-servics-list-2":{"title":"","count":"6","posts_order":"DESC"},"custom_html-2":{"title":"","content":"<div class=\"sidebar__widget widget__contact\">\r\n                            <div class=\"sidebar__widget-contact overflow-hidden\">\r\n                                <div class=\"sidebar__widget-contact__thumb\">\r\n                                    <img src=\"https:\/\/wp.rrdevs.net\/artima\/wp-content\/uploads\/2024\/10\/news.jpg\" alt=\"image not found\">\r\n                                    <div class=\"sidebar__widget-contact__content\">\r\n\r\n                                        <div class=\"sidebar__widget-contact__icon\">\r\n                                            <svg width=\"23\" height=\"23\" fill=\"none\" xmlns=\"http:\/\/www.w3.org\/2000\/svg\">\r\n                                                <path d=\"M13.9381 5C14.9149 5.19057 15.8125 5.66826 16.5162 6.37194C17.2199 7.07561 17.6976 7.97326 17.8881 8.95M13.9381 1C15.9674 1.22544 17.8597 2.13417 19.3044 3.57701C20.749 5.01984 21.6601 6.91101 21.8881 8.94M20.8881 16.92V19.92C20.8892 20.1985 20.8322 20.4742 20.7206 20.7293C20.6091 20.9845 20.4454 21.2136 20.2402 21.4019C20.035 21.5901 19.7927 21.7335 19.5289 21.8227C19.265 21.9119 18.9855 21.9451 18.7081 21.92C15.631 21.5856 12.6751 20.5341 10.0781 18.85C7.66194 17.3147 5.61345 15.2662 4.07812 12.85C2.38809 10.2412 1.33636 7.27099 1.00812 4.18C0.983127 3.90347 1.01599 3.62476 1.10462 3.36162C1.19324 3.09849 1.33569 2.85669 1.52288 2.65162C1.71008 2.44655 1.93792 2.28271 2.19191 2.17052C2.44589 2.05833 2.72046 2.00026 2.99812 2H5.99812C6.48342 1.99522 6.95391 2.16708 7.32188 2.48353C7.68985 2.79999 7.93019 3.23945 7.99812 3.72C8.12474 4.68007 8.35957 5.62273 8.69812 6.53C8.83266 6.88792 8.86178 7.27691 8.78202 7.65088C8.70227 8.02485 8.51698 8.36811 8.24812 8.64L6.97812 9.91C8.40167 12.4135 10.4746 14.4864 12.9781 15.91L14.2481 14.64C14.52 14.3711 14.8633 14.1858 15.2372 14.1061C15.6112 14.0263 16.0002 14.0555 16.3581 14.19C17.2654 14.5286 18.2081 14.7634 19.1681 14.89C19.6539 14.9585 20.0975 15.2032 20.4146 15.5775C20.7318 15.9518 20.9003 16.4296 20.8881 16.92Z\" stroke=\"white\" stroke-width=\"1.5\" stroke-linecap=\"round\" stroke-linejoin=\"round\"><\/path>\r\n                                            <\/svg>                                                \r\n                                        <\/div>\r\n\r\n                                        <span>Need help?<\/span>\r\n                                        <a href=\"tel:8085550111\">+(808) 555-0111<\/a>\r\n                                        <p class=\"mb-0\">Lorem Ipsum is simply is dumiomy is text Lorem Ipsum is simply is ou our o dummy text<\/p>\r\n                                    <\/div>\r\n                                <\/div>\r\n                            <\/div>\r\n                        <\/div>"}},"footer-1":{"rr_subscriber_widget-2":{"subscribe_style":"","mailchimp_shortcode":"[mc4wp_form id=1236]","mailchimp_text":"we are passionate about creating exceptional interior spaces that inspire, delight, and enhance the lives of our clients.","image_box_image":"https:\/\/wp.rrdevs.net\/artima\/wp-content\/uploads\/2024\/10\/logo-2.png"}},"footer-2":{"nav_menu-2":{"title":"Company","nav_menu":4}},"footer-3":{"nav_menu-3":{"title":"Resources","nav_menu":3}},"footer-4":{"artima_sidebar_instagram_post-2":{"title":"Instagram ","gallery_img_1":"https:\/\/wp.rrdevs.net\/artima\/wp-content\/uploads\/2024\/10\/instagram-1.png","gallery_img_2":"https:\/\/wp.rrdevs.net\/artima\/wp-content\/uploads\/2024\/09\/instagram-2-1.png","gallery_img_3":"https:\/\/wp.rrdevs.net\/artima\/wp-content\/uploads\/2024\/09\/instagram-3-1.png","gallery_img_4":"https:\/\/wp.rrdevs.net\/artima\/wp-content\/uploads\/2024\/09\/instagram-4-1.png","gallery_img_5":"","gallery_img_6":"","instagram":"https:\/\/www.instagram.com\/","instagram_2":"https:\/\/www.instagram.com\/","instagram_3":"https:\/\/www.instagram.com\/","instagram_4":"https:\/\/www.instagram.com\/"}},"footer-2-1":{"medinet_info_widget-2":{"title":"","description":"Inoterior design consultancy firm that brings sensitivity to the design top restaurants, hotels Read more!","phone_number":"+1-2353-4352-555","phone_number_url":"123534352555","image_box_image":"https:\/\/wp.rrdevs.net\/artima\/wp-content\/uploads\/2024\/10\/logo-2.png"}},"footer-2-2":{"nav_menu-4":{"title":"Useful Links","nav_menu":25}},"footer-2-3":{"rr-latest-posts-footer-thumb-2":{"title":"Recent Posts","count":"2","posts_order":"DESC"}},"footer-2-4":{"kingfact_contact_info_widget-2":{"title":"Contact Us","address":"example@gmail.com","address_url":"","email":"example@gmail.com","phone_number":"+888 (123) 869523","phone_number_url":"888123869523","location_text":"1058 Helton Ave, Berlin.","location_url":""}},"footer-3-1":{"rr_subscriber_widget-3":{"subscribe_style":"","mailchimp_shortcode":"[mc4wp_form id=1236]","mailchimp_text":"we are passionate about creating exceptional interior spaces that inspire, delight, and enhance the lives of our clients.","image_box_image":"https:\/\/wp.rrdevs.net\/artima\/wp-content\/uploads\/2024\/10\/logo-2.png"}},"footer-3-2":{"nav_menu-5":{"title":"Company","nav_menu":24}},"footer-3-3":{"nav_menu-6":{"title":"Useful Links","nav_menu":10}},"footer-3-4":{"kingfact_contact_info_widget-3":{"title":"Contact Us","email":"example@gmail.com","phone_number":"+888 (123) 869523","phone_number_url":"888123869523","location_text":"1058 Helton Ave, Stky Berlin, Germany","location_url":"https:\/\/maps.app.goo.gl\/1N77c8d8zieLRaot7"}}}